stack/__init__.py
stack/app.py
stack/browser.py
stack/cli.py
stack/commands/__init__.py
stack/commands/base.py
stack/commands/build.py
stack/commands/check.py
stack/commands/checkout.py
stack/commands/clone.py
stack/commands/down.py
stack/commands/init.py
stack/commands/logs.py
stack/commands/packages.py
stack/commands/pull.py
stack/commands/push.py
stack/commands/reup.py
stack/commands/secrets.py
stack/commands/shell.py
stack/commands/status.py
stack/commands/test.py
stack/commands/up.py
stack/commands/update.py
hmsdbmitc_stack-0.5.0.dist-info/METADATA
hmsdbmitc_stack-0.5.0.dist-info/WHEEL
hmsdbmitc_stack-0.5.0.dist-info/entry_points.txt
hmsdbmitc_stack-0.5.0.dist-info/top_level.txt
hmsdbmitc_stack-0.5.0.dist-info/RECORD
