Metadata-Version: 2.1
Name: hmsdbmitc-stack
Version: 0.5.0
Summary: A command line program to manage a Docker stack.
Home-page: https://github.com/hms-dbmi/stack.git
Author: HMS DBMI Tech-core
Author-email: bryan_larson@hms.harvard.edu
License: UNLICENSE
Keywords: cli
Platform: UNKNOWN
Classifier: Intended Audience :: Developers
Classifier: Topic :: Utilities
Classifier: License :: Public Domain
Classifier: Natural Language :: English
Classifier: Operating System :: OS Independent
Classifier: Programming Language :: Python :: 2
Classifier: Programming Language :: Python :: 2.6
Classifier: Programming Language :: Python :: 2.7
Classifier: Programming Language :: Python :: 3
Classifier: Programming Language :: Python :: 3.2
Classifier: Programming Language :: Python :: 3.3
Classifier: Programming Language :: Python :: 3.4
Classifier: Programming Language :: Python :: 3.5
Classifier: Programming Language :: Python :: 3.6
Requires-Dist: boto3 (>=1.13.3)
Requires-Dist: colorlog (>=4.0.2)
Requires-Dist: docker (>=3.7.2)
Requires-Dist: docopt (>=0.6.2)
Requires-Dist: fhirclient (==3.2.0)
Requires-Dist: furl (>=2.0.0)
Requires-Dist: mysql-connector-python (>=8.0.16)
Requires-Dist: python-dateutil (>=2.6.1)
Requires-Dist: PyYAML (>=5.1)
Requires-Dist: requests (>=2.21.0)
